pdf2images/__init__.py
pdf2images/packdet.py
pdf2images/pdf2images.py
pdf2images-0.0.6.data/scripts/pdf2images
pdf2images-0.0.6.dist-info/LICENSE
pdf2images-0.0.6.dist-info/METADATA
pdf2images-0.0.6.dist-info/WHEEL
pdf2images-0.0.6.dist-info/top_level.txt
pdf2images-0.0.6.dist-info/RECORD
