Metadata-Version: 2.1
Name: pdf2images
Version: 0.0.6
Summary: Convert PDF file to image files ROBUSTLY.
Home-page: https://github.com/zxytim/pdf2images
Author: Xinyu Zhou
Author-email: zxytim@gmail.com
License: UNKNOWN
Platform: UNKNOWN
Classifier: Programming Language :: Python :: 3
Classifier: License :: OSI Approved :: BSD License
Classifier: Intended Audience :: Developers
Classifier: Intended Audience :: Science/Research
Classifier: Topic :: Software Development :: Libraries :: Python Modules
Requires-Python: >=3.5
Requires-Dist: distro (>=1.4.0)
Requires-Dist: loguru (>=0.4.0)
Requires-Dist: plumbum (>=1.6.8cv)
Requires-Dist: preview-generator (>=0.13)
Requires-Dist: tqdm (>=4.41.0)
Requires-Dist: Wand (>=0.5.9)
